Metadata-Version: 2.1
Name: django-rated-reviews
Version: 1.0.1
Summary: Rated reviews for Django
Home-page: https://github.com/andreynovikov/django-rated-reviews/tree/master
Author: Andrey Novikov
Author-email: novikov@gmail.com
License: MIT
Project-URL: Tracker, https://github.com/andreynovikov/django-rated-reviews/issues
Project-URL: Documentation, https://django-rated-reviews.readthedocs.io/
Project-URL: Source, https://github.com/andreynovikov/django-rated-reviews/
Platform: UNKNOWN
Classifier: Development Status :: 6 - Mature
Classifier: Framework :: Django
Classifier: Programming Language :: Python
Classifier: Programming Language :: Python :: 3
Classifier: License :: OSI Approved :: MIT License
Classifier: Operating System :: OS Independent
